{
  "excerpt": "Glücklich und dankbar blicken wir auf zwei erfolgreiche Jahre zurück. Wir halten einen Moment inne und feiern mit unseren Kunden, Freunden & Kontakten – und mit dir!",
  "slug": "english",
  "date": "2022-07-22T13:30:24.306Z",
  "markdown": "Glücklich und dankbar blicken wir auf zwei erfolgreiche Jahre zurück. Wir halten einen Moment inne und feiern mit unseren Kunden, Freunden & Kontakten – und mit dir! \n\nMit der positiven Resonanz unserer Kunden entwickeln wir uns immer weiter. Voller Freude möchten wir uns bei euch für die schönsten Geschenke bedanken – euer Vertrauen und eure wunderbaren Zitate. Wir wünschen uns, euch weiterhin und auch dich mit unseren strategischen Insights und unserer Expertise zum Strahlen zu bringen. \n\nFür deine Marketingziele, deinen Erfolg und Freiraum stellen wir neue und bewährte Module auf unserer brandneuen Webseite [www.bluestarmarketing.de](http://www.bluestarmarketing.de) vor. Nimm dir einen Moment Zeit und finde heraus, welche deiner Projekte mit uns den entscheidenden Kick bekommen. \n\n**Starte deine Wunschrakete!**",
  "previewimage": "/media/bluestar_birthday_2_starnews_wunschrakete.jpg",
  "title": "Konfettiregen, Trommelwirbel und Wunderkerzen: Für dich sind wir Blue Star Marketing",
  "credit": "Bilder von: ngupakarti – stock.adobe.com, kitsana – stock.adobe.com\u0000\u0000",
  "image": "/media/bluestar_birthday_2_starnews_wunschrakete_highlight.jpg",
  "categories": [
    "B2B-Marketing",
    "Marketingstrategie"
  ]
}