{
  "de": {
    "rewrites": [
      {
        "from": "/en/contact",
        "to": "/en/kontakt"
      },
      {
        "from": "/en/b2bmarketingstrategy",
        "to": "/en/b2bmarketingstrategie"
      },
      {
        "from": "/en/marketingcampaigns",
        "to": "/en/marketingkampagnen"
      },
      {
        "from": "/en/foryou",
        "to": "/en/fuerdich"
      },
      {
        "from": "/en/customers",
        "to": "/en/kunden"
      },
      {
        "from": "/en/legal/privacy",
        "to": "/en/rechtliches/privacy"
      },
      {
        "from": "/en/legal/imprint",
        "to": "/en/rechtliches/imprint"
      }
    ]
  },
  "en": {}
}